hikyuu/LICENSE.txt
hikyuu/__init__.py
hikyuu/__init__.pyi
hikyuu/core.py
hikyuu/core.pyi
hikyuu/extend.py
hikyuu/extend.pyi
hikyuu/hub.py
hikyuu/hub.pyi
hikyuu/interactive.py
hikyuu/analysis/__init__.py
hikyuu/analysis/__init__.pyi
hikyuu/analysis/analysis.py
hikyuu/analysis/analysis.pyi
hikyuu/config/__init__.py
hikyuu/config/block/__init__.py
hikyuu/config/block/dybk.ini
hikyuu/config/block/gnbk.ini
hikyuu/config/block/hybk.ini
hikyuu/config/block/self.ini
hikyuu/config/block/zsbk.ini
hikyuu/cpp/__init__.py
hikyuu/cpp/__init__.pyi
hikyuu/cpp/boost_date_time-mt.dll
hikyuu/cpp/boost_serialization-mt.dll
hikyuu/cpp/boost_system-mt.dll
hikyuu/cpp/boost_wserialization-mt.dll
hikyuu/cpp/concrt140.dll
hikyuu/cpp/core310.pyd
hikyuu/cpp/core310.pyi
hikyuu/cpp/core311.pyd
hikyuu/cpp/core311.pyi
hikyuu/cpp/core312.pyd
hikyuu/cpp/core312.pyi
hikyuu/cpp/core313.pyd
hikyuu/cpp/core313.pyi
hikyuu/cpp/hikyuu.dll
hikyuu/cpp/hikyuu.lib
hikyuu/cpp/hku_hdf5.dll
hikyuu/cpp/hku_hdf5_cpp.dll
hikyuu/cpp/hku_hdf5_hl.dll
hikyuu/cpp/hku_hdf5_hl_cpp.dll
hikyuu/cpp/libcrypto-1_1-x64.dll
hikyuu/cpp/libmysql.dll
hikyuu/cpp/libssl-1_1-x64.dll
hikyuu/cpp/msvcp140.dll
hikyuu/cpp/msvcp140_1.dll
hikyuu/cpp/msvcp140_2.dll
hikyuu/cpp/msvcp140_atomic_wait.dll
hikyuu/cpp/msvcp140_codecvt_ids.dll
hikyuu/cpp/sqlite3.dll
hikyuu/cpp/vcruntime140.dll
hikyuu/cpp/vcruntime140_1.dll
hikyuu/cpp/i18n/__init__.py
hikyuu/cpp/i18n/zh_CN/__init__.py
hikyuu/cpp/i18n/zh_CN/hikyuu.mo
hikyuu/data/__init__.py
hikyuu/data/common.py
hikyuu/data/common_clickhouse.py
hikyuu/data/common_h5.py
hikyuu/data/common_mysql.py
hikyuu/data/common_pytdx.py
hikyuu/data/common_sqlite3.py
hikyuu/data/download_block.py
hikyuu/data/em_block_to_clickhouse.py
hikyuu/data/em_block_to_mysql.py
hikyuu/data/em_block_to_sqlite.py
hikyuu/data/hku_config_template.py
hikyuu/data/pytdx_finance_to_clickhouse.py
hikyuu/data/pytdx_finance_to_mysql.py
hikyuu/data/pytdx_finance_to_sqlite.py
hikyuu/data/pytdx_to_clickhouse.py
hikyuu/data/pytdx_to_h5.py
hikyuu_noarrow-2.6.9.1.dist-info/METADATA
hikyuu_noarrow-2.6.9.1.dist-info/WHEEL
hikyuu_noarrow-2.6.9.1.dist-info/entry_points.txt
hikyuu_noarrow-2.6.9.1.dist-info/top_level.txt
hikyuu_noarrow-2.6.9.1.dist-info/RECORD
