Metadata-Version: 2.4
Name: hikyuu-noarrow
Version: 2.6.9.1
Summary: Hikyuu Quant Framework for System Trading Analysis and backtester
Home-page: http://hikyuu.org/
Author: fasiondog
Author-email: fasiondog@sina.com
License: MIT
Keywords: quant,trade,System Trading,backtester,量化,程序化交易,量化交易,系统交易
Platform: Independant
Classifier: Development Status :: 5 - Production/Stable
Classifier: Intended Audience :: Developers
Classifier: Topic :: Software Development :: Libraries :: Python Modules
Classifier: Topic :: Office/Business :: Financial
Classifier: Topic :: Office/Business :: Financial :: Investment
Classifier: Topic :: Scientific/Engineering :: Mathematics
Classifier: License :: OSI Approved :: MIT License
Classifier: Operating System :: Microsoft :: Windows
Classifier: Operating System :: POSIX :: Linux
Classifier: Operating System :: MacOS :: MacOS X
Classifier: Programming Language :: Python :: 3
Classifier: Programming Language :: Python :: 3.10
Classifier: Programming Language :: Python :: 3.11
Classifier: Programming Language :: Python :: 3.12
Classifier: Programming Language :: Python :: 3.13
Requires-Dist: click
Requires-Dist: numpy>=2.0
Requires-Dist: matplotlib>=3.5.0
Requires-Dist: seaborn>=0.13.2
Requires-Dist: pandas>=2.3.0
Requires-Dist: pytdx
Requires-Dist: PySide6>=6.8.0
Requires-Dist: tables>=3.9.0
Requires-Dist: bokeh>=3.4.0
Requires-Dist: gitpython
Requires-Dist: SQLAlchemy
Requires-Dist: mysql-connector-python
Requires-Dist: pyperclip
Requires-Dist: requests
Requires-Dist: flatbuffers>=24.3.25
Requires-Dist: pynng
Requires-Dist: akshare
Requires-Dist: pyecharts>=2.0.9
Requires-Dist: pipdeptree
Requires-Dist: h5py>=3.14.0
Requires-Dist: tqdm>=4.67.1
Requires-Dist: clickhouse-connect>=0.9.2
Requires-Dist: zstandard>=0.25
Dynamic: author
Dynamic: author-email
Dynamic: classifier
Dynamic: description
Dynamic: description-content-type
Dynamic: home-page
Dynamic: keywords
Dynamic: license
Dynamic: platform
Dynamic: requires-dist
Dynamic: summary
